fmg_discovery/__init__.py
fmg_discovery/__main__.py
fmg_discovery/environments.py
fmg_discovery/exceptions.py
fmg_discovery/file_service_discovery.py
fmg_discovery/fmg_api.py
fmg_discovery/fmg_collector.py
fmg_discovery/fmg_metrics.py
fmg_discovery/fmglogging.py
fmg_discovery/fw.py
fmg_discovery/http_service_discovery.py
fmg_discovery/transform.py
fortigate_exporter_discovery-0.5.0.dist-info/LICENSE
fortigate_exporter_discovery-0.5.0.dist-info/METADATA
fortigate_exporter_discovery-0.5.0.dist-info/NOTICE
fortigate_exporter_discovery-0.5.0.dist-info/WHEEL
fortigate_exporter_discovery-0.5.0.dist-info/top_level.txt
fortigate_exporter_discovery-0.5.0.dist-info/RECORD
